<?xml version="1.0" encoding="UTF-8"?>
<ServerManagerConfiguration>
  <ProxyGroup name="sources">
    <SourceProxy name="ttkTriangulationReader"
                 class="ttkTriangulationReader"
                 label="TTK TriangulationReader">
      <Documentation
          long_help="TTK TriangulationReader"
          short_help="TTK TriangulationReader">
        This source reads the content of an already preconditioned TTK
        Explicit Triangulation File to import it into the current
        dataset.
      </Documentation>

      <StringVectorProperty name="TriangulationFilePath"
                            label="Triangulation File Path"
                            animateable="0"
                            command="SetTriangulationFilePath"
                            number_of_elements="1">
        <Documentation>Path to a TTK Triangulation File.</Documentation>
        <FileListDomain name="files" />
        <Hints>
          <UseDirectoryName />
        </Hints>
      </StringVectorProperty>

      <PropertyGroup panel_widget="Line" label="Input Options">
        <Property name="TriangulationFilePath" />
      </PropertyGroup>

      ${DEBUG_WIDGETS}

      <Hints>
        <ShowInMenu category="TTK" />
      </Hints>
    </SourceProxy>
  </ProxyGroup>
</ServerManagerConfiguration>
